pathtraits/__init__.py
pathtraits/access.py
pathtraits/cli.py
pathtraits/db.py
pathtraits/pathpair.py
pathtraits/scan.py
pathtraits-0.5.1.dist-info/METADATA
pathtraits-0.5.1.dist-info/WHEEL
pathtraits-0.5.1.dist-info/entry_points.txt
pathtraits-0.5.1.dist-info/RECORD
