Metadata-Version: 2.4
Name: pathtraits
Version: 0.5.1
Summary: Attributes of files and directories stored in YAML sidecar files
License: MIT
Author: Daniel Loos
Requires-Python: >=3.12,<4.0
Classifier: License :: OSI Approved :: MIT License
Classifier: Programming Language :: Python :: 3
Classifier: Programming Language :: Python :: 3.12
Classifier: Programming Language :: Python :: 3.13
Classifier: Programming Language :: Python :: 3.14
Requires-Dist: PyYAML (>=6.0,<7.0)
Requires-Dist: click (>=8.1,<9.0)
Requires-Dist: inotify (>=0.2,<0.3)
